README.rst
coolhammer.py
setup.cfg
setup.py
chammer/__init__.py
chammer/debug_util.py
chammer/event_util.py
chammer/file_util.py
chammer/url_util.py
pychammer.egg-info/PKG-INFO
pychammer.egg-info/SOURCES.txt
pychammer.egg-info/dependency_links.txt
pychammer.egg-info/entry_points.txt
pychammer.egg-info/requires.txt
pychammer.egg-info/top_level.txt